dataclass_csv/__init__.py
dataclass_csv/dataclass_reader.py
dataclass_csv/dataclass_writer.py
dataclass_csv/decorators.py
dataclass_csv/exceptions.py
dataclass_csv/field_mapper.py
dataclass_csv/header_mapper.py
dataclass_csv2-0.1.0.dist-info/METADATA
dataclass_csv2-0.1.0.dist-info/WHEEL
dataclass_csv2-0.1.0.dist-info/licenses/AUTHORS.md
dataclass_csv2-0.1.0.dist-info/licenses/LICENSE
dataclass_csv2-0.1.0.dist-info/RECORD
