Metadata-Version: 2.4
Name: dataclass-csv2
Version: 0.1.0
Summary: Map CSV data into dataclasses
Project-URL: Homepage, https://github.com/kraktus/dataclass-csv2
Project-URL: Issue Tracker, https://github.com/kraktus/dataclass-csv2/issues
Author-email: Kraktus <kraktus@users.noreply.github.com>, Daniel Furtado <daniel@dfurtado.com>
License-File: AUTHORS.md
License-File: LICENSE
Keywords: csv,dataclass,dataclass-csv,dataclasses
Classifier: Development Status :: 5 - Production/Stable
Classifier: Environment :: Console
Classifier: Intended Audience :: Developers
Classifier: License :: OSI Approved :: BSD License
Classifier: Natural Language :: English
Classifier: Operating System :: MacOS :: MacOS X
Classifier: Operating System :: Microsoft :: Windows
Classifier: Operating System :: POSIX
Classifier: Operating System :: Unix
Classifier: Programming Language :: Python :: 3 :: Only
Classifier: Programming Language :: Python :: 3.7
Requires-Python: >=3.7
